{"type":"fletching-additions:fletching_recipe","outputItem":"fletching-additions:custom_arrow","outputAmount":6,"inputTip":{"item":"minecraft:carrot"},"inputStick":{"item":"minecraft:bamboo"},"inputFins":{"item":"minecraft:firework_rocket"},"inputEffect":{"item":"minecraft:glowstone_dust"},"outputNbt":"{display:{Name:'[{\"text\":\"Carrot Tipped Rocket Powered Spectral Arrow with a Bamboo Core\",\"italic\":false}]'},flySpeed:2.25f,gravityMult:1.09375f,drawSpeed:0.25f,drawMinMult:2f,damageMult:0.21875f,gameFlags:[\"inheritFireworkNBT\"],renderParts:[\n        {mode:\"texture\",data:\"165\",type:\"t\"},\n        {mode:\"texture\",data:\"3\",type:\"s\"},\n        {mode:\"texture\",data:\"162\",type:\"f\",extraData:\"h\"}\n    ],effects:[{id:\"minecraft:glowing\",duration:10,amplifier:1}],particles:[\"minecraft:instant_effect\"],itemTextureData:2.700180227787526e-38f,afterRocketItemTextureData:2.699964988343406e-38f}"}